aws_easy_mfa/__init__.py
aws_easy_mfa/main.py
aws_easy_mfa/utilities.py
aws_easy_mfa-0.1.1.dist-info/METADATA
aws_easy_mfa-0.1.1.dist-info/WHEEL
aws_easy_mfa-0.1.1.dist-info/RECORD
