Metadata-Version: 2.1
Name: aws-easy-mfa
Version: 0.1.1
Summary: a simple python decorator to make using aws mfa super easy with boto3
Home-page: https://github.com/jermwatt/aws_easy_mfa
Author: Jeremy Watt
Author-email: jermwatt@gmail.com
Requires-Python: >=3.9,<4.0
Classifier: Programming Language :: Python :: 3
Classifier: Programming Language :: Python :: 3.9
Classifier: Programming Language :: Python :: 3.10
Classifier: Programming Language :: Python :: 3.11
Requires-Dist: boto3 (>=1.26.139,<2.0.0)
